{
  "products": [
    {
      "id": 0,
      "imageSrc": "/p1.jpeg",
      "title": "Produto 1",
      "description": "Descrição do Produto",
      "price": 12.00,
      "sales": 10
    },
    {
      "id": 1,
      "imageSrc": "/p1.jpeg",
      "title": "Produto 2",
      "description": "Descrição do Produto",
      "price": 65.00,
      "sales": 9
    },
    {
      "id": 2,
      "imageSrc": "/p1.jpeg",
      "title": "Produto 3",
      "description": "Descrição do Produto",
      "price": 5.00,
      "oldPrice": 10.00,
      "sales": 8
    },
    {
      "id": 3,
      "imageSrc": "/p1.jpeg",
      "title": "Produto 4",
      "description": "Descrição do Produto",
      "price": 109.00,
      "oldPrice": 150.00,
      "sales": 7
    },
    {
      "id": 4,
      "imageSrc": "/p1.jpeg",
      "title": "Produto 5",
      "description": "Descrição do Produto",
      "price": 49.00,
      "sales": 6
    },
    {
      "id": 5,
      "imageSrc": "/p1.jpeg",
      "title": "Produto 6",
      "description": "Descrição do Produto",
      "price": 49.00,
      "sales": 5
    }
  ]
}